pybuilder_read_profile_properties/__init__.py
pybuilder_read_profile_properties-1.0.0.dist-info/DESCRIPTION.rst
pybuilder_read_profile_properties-1.0.0.dist-info/METADATA
pybuilder_read_profile_properties-1.0.0.dist-info/RECORD
pybuilder_read_profile_properties-1.0.0.dist-info/WHEEL
pybuilder_read_profile_properties-1.0.0.dist-info/metadata.json
pybuilder_read_profile_properties-1.0.0.dist-info/namespace_packages.txt
pybuilder_read_profile_properties-1.0.0.dist-info/top_level.txt
pybuilder_read_profile_properties-1.0.0.dist-info/zip-safe
